zpp_browser/__init__.py
zpp_browser/browser.py
zpp_browser-1.0.2.dist-info/LICENSE
zpp_browser-1.0.2.dist-info/METADATA
zpp_browser-1.0.2.dist-info/WHEEL
zpp_browser-1.0.2.dist-info/top_level.txt
zpp_browser-1.0.2.dist-info/RECORD
