Metadata-Version: 2.1
Name: zpp_browser
Version: 1.0.2
Summary: Browser (Explorateur) de fichier en cli
Home-page: https://github.com/ZephyrOff/zpp_browser
Author: 
License: MIT License
Project-URL: Documentation, https://github.com/ZephyrOff/zpp_browser
Platform: ALL
License-File: LICENSE
